imgtopdfeasy/__init__.py
imgtopdfeasy/__main__.py
imgtopdfeasy/customerrors.py
imgtopdfeasy/img2pdf.py
imgtopdfeasy-0.3.0.dist-info/entry_points.txt
imgtopdfeasy-0.3.0.dist-info/LICENSE
imgtopdfeasy-0.3.0.dist-info/WHEEL
imgtopdfeasy-0.3.0.dist-info/METADATA
imgtopdfeasy-0.3.0.dist-info/RECORD
