Metadata-Version: 2.1
Name: imgtopdfeasy
Version: 0.3.0
Summary: This is command line utility to convert images in a directory to  PDF file.
Home-page: https://github.com/naveen521kk/img2pdf
License: MIT
Author: Naveen
Author-email: naveen521kk@gmail.com
Requires-Python: >=3.6,<4.0
Classifier: License :: OSI Approved :: MIT License
Classifier: Programming Language :: Python :: 3
Classifier: Programming Language :: Python :: 3.10
Classifier: Programming Language :: Python :: 3.6
Classifier: Programming Language :: Python :: 3.7
Classifier: Programming Language :: Python :: 3.8
Classifier: Programming Language :: Python :: 3.9
Requires-Dist: Pillow (>=8,<9)
Project-URL: Repository, https://github.com/naveen521kk/img2pdf
